{
  "main": {
    "name":"Meghanath Ponoly Balakrishnan",
    "occupation":"Full Stack Web Developer",
    "description":"A developer with a strong interest in projects requiring conceptual and analytical thinking. I enjoy designing websites with end users in mind.",
    "image":"profilepic.jpg",
    "bio":"I was working on Bell as telecommunication technician before i pursue web development. My day to day life in Bell was pretty much troubleshooting issues on network elements and connecting both end user and central office. Working on the physical layer of networking made me curious to know about software side. That made me took this path. Moreover I am a professional photographer and graphic designer, so i wanted to combine these experiences together and create interesting experiences for users",
    "contactmessage":"Please send me message",
    "email": "meghanath.balaji@gmail.com",
    "phone": "647-528-7504",
    "address":{
      "street":"2233 Eglinton Avenue East",
      "city":"Toronto",
      "state":"Ontario",
      "zip": "M1K2M9"
    },
    "website": "https://500px.com/meghanathpbala",
    "resumedownload":"https://www.canva.com/design/DAD0_YgjkkY/80WF1PBJOuVAISfzBrbAKQ/view?utm_content=DAD0_YgjkkY&utm_campaign=designshare&utm_medium=link&utm_source=sharebutton",
    "social":[
      
      {
        "name":"linkedin",
        "url":"https://www.linkedin.com/in/meghanathponoly/",
        "className":"fa fa-linkedin"
      },
     
      {
        "name":"github",
        "url":"https://github.com/Meghanath91",
        "className":"fa fa-github"
      }
    ]
  },
  "resume":{
    "skillmessage":"i am a full stack developer with good knowledge in database, backend, frontend",
    "education":[
      {
        "school":"Lighthouse Labs",
        "degree":"Full Stack Web  Developer bootCamp",
        "graduated":"April 2020",
        "description":"Describe your experience at school, what you learned, what useful skills you have acquired etc."
      },
      {
        "school":"India Options",
        "degree":"Software Testing & Automation Diploma",
        "graduated":"December 2014",
        "description":"Describe your experience at school, what you learned, what useful skills you have acquired etc."
      },
      {
        "school":"Centennial",
        "degree":"Energy Systems Engineering Advanced Diploma",
        "graduated":"May 2016",
        "description":"Describe your experience at school, what you learned, what useful skills you have acquired etc."
      },
      {
        "school":"Calicut University",
        "degree":"Bachelor of Technology in Electrical & Electronics Engineering ",
        "graduated":"May 2013",
        "description":"Describe your experience at school, what you learned, what useful skills you have acquired etc."
      }
    ],
    "work":[
      {
        "company":"Bell Canada",
        "title":"Telecommunications Technician",
        "years":"May 2017 - Present",
        "description":"Installation and maintenance of network systems .Troubleshoot complex telecommunications systems.Started as technician and promoted to Mentor and Trainer.Achieved merit of excellence award for 2018"
      },
      {
        "company":"Grasshopper Solar",
        "title":"Quality Assurance Technologist",
        "years":"June 2016 - September 2016",
        "description":"Testing & commissioning of Solar project. Updated the firmware of inverters"
      }
    ],
    "skills":[
      {
        "name":"Git",
        "level":"60%"
      },
      {
        "name":"Node.js",
        "level":"55%"
      },
      {
        "name":"React.Js",
        "level":"50%"
      },
      {
        "name":"CSS",
        "level":"90%"
      },
      {
        "name":"HTML5",
        "level":"80%"
      },
      {
        "name":"Express",
        "level":"50%"
      },
      {
        "name":"PostgreSQL",
        "level":"80%"
      },
      {
        "name":"Ruby on Rails",
        "level":"50%"
      },
      {
        "name":"Jest",
        "level":"80%"
      },
      {
        "name":"Linux",
        "level":"80%"
      }
    ]
  },
  "portfolio":{
    "projects": [
      {
        "title":"Custom-fitness",
        "category":"An app that allows to connect trainers and students where trainers can create custom workouts and students can complete it. ",
        "image":"canadian-wanderlust.jpg",
        "url":"https://www.canadianwanderlust.com"
      },
      {
        "title":"Rumours-Lounge & Restaurant ",
        "category":"An interactive & responsive web app for restaurant where users can view the menu,submit the order and receive a confirmation SMS & call.",
        "image":"fury-fighting-gear.jpg",
        "url":"https://rumours.herokuapp.com/"
      },
      {
        "title":"Interview Scheduler",
        "category":"An interactive web app to manage interview schedules",
        "image":"original-thai-food.jpg",
        "url":"https://github.com/Meghanath91/scheduler"
      },
      {
        "title":"Portfolio Website",
        "category":"A React based resume website template",
        "image":"resume-website.jpg",
        "url":"http://www.timbakerdev.com"
      },
      {
        "title":"Smirkspace",
        "category":"(MVP Only) A React and Meteor based chat University project.",
        "image":"smirkspace.jpg",
        "url":"http://www.smirkspace.com"
      }
    ]
  },
  "testimonials":{
    "testimonials":[
      {
        "text":"Here you should write some nice things that someone has said about you. No lies though, employers can tell when you are lying.",
        "user":"Kareem Abdul Jabbar"
      },
      {
        "text":"That Tim Baker must be one of the most brilliant developers I've ever met! It is amazing that nobody has hired him yet. Hey you, you should hire this guy, he may be fresh out of University and have zero on the job experience but I am confident that he will be one of your best developers in no time!",
        "user":"Steve Wozniak... impersonator"
      }
    ]
  }
}
